README.rst
setup.py
BeautifulTime/__init__.py
BeautifulTime/beautiful.py
BeautifulTime/test.py
beautiful_time.egg-info/PKG-INFO
beautiful_time.egg-info/SOURCES.txt
beautiful_time.egg-info/dependency_links.txt
beautiful_time.egg-info/top_level.txt