Metadata-Version: 1.0
Name: beautiful-time
Version: 0.2
Summary: date string, datetime, time and timestamp converter
Home-page: https://github.com/restran/beautiful-time
Author: restran
Author-email: grestran@gmail.com
License: MIT License
Keywords: time,datetime,converter
Platform: any
